MANIFEST.in
README.rst
setup.cfg
setup.py
enasearch/__init__.py
enasearch/__main__.py
enasearch/cli.py
enasearch.egg-info/PKG-INFO
enasearch.egg-info/SOURCES.txt
enasearch.egg-info/dependency_links.txt
enasearch.egg-info/entry_points.txt
enasearch.egg-info/requires.txt
enasearch.egg-info/top_level.txt
enasearch_data/__init__.py
enasearch_data/display_options.p
enasearch_data/download_options.p
enasearch_data/filter_types.p
enasearch_data/result_description.p
enasearch_data/taxonomy_results.p
tests/__init__.py
tests/test_cli.py
tests/test_enasearch.py