Metadata-Version: 1.1
Name: enasearch
Version: 0.1.1
Summary: A Python library for interacting with ENA's API
Home-page: https://github.com/bebatut/enasearch
Author: Berenice Batut
Author-email: berenice.batut@gmail.com
License: MIT
Keywords: api api-client ena
Platform: UNKNOWN
Classifier: Development Status :: 2 - Pre-Alpha
Classifier: Environment :: Web Environment
Classifier: License :: OSI Approved :: MIT License
Classifier: Programming Language :: Python :: 3
Classifier: Intended Audience :: Developers
Classifier: Operating System :: OS Independent
Classifier: Topic :: Scientific/Engineering
Classifier: Programming Language :: Python :: 2
Classifier: Programming Language :: Python :: 2.7
Classifier: Programming Language :: Python :: 3
Classifier: Programming Language :: Python :: 3.4
Classifier: Programming Language :: Python :: 3.5
Classifier: Programming Language :: Python :: 3.6
